README.md
setup.py
loraspi/LoRaRelay.py
loraspi/LoRaRxTx.py
loraspi/LoRaTransparent.py
loraspi/LoRaWoR.py
loraspi/__init__.py
loraspi.egg-info/PKG-INFO
loraspi.egg-info/SOURCES.txt
loraspi.egg-info/dependency_links.txt
loraspi.egg-info/requires.txt
loraspi.egg-info/top_level.txt