Metadata-Version: 2.1
Name: loraspi
Version: 1.7
Summary: library for lora stuff
Home-page: https://github.com/nbdy/loraspi
Author: Pascal Eberlein
Author-email: pascal@eberlein.io
License: UNKNOWN
Keywords: waveshare lora library
Platform: UNKNOWN
Classifier: Intended Audience :: Developers
Classifier: Topic :: Software Development :: Build Tools
Classifier: License :: OSI Approved :: MIT License
